rework/__init__.py
rework/__pycache__/__init__.cpython-311.pyc
rework/contrib/__init__.py
rework/contrib/users/__init__.py
rework/contrib/users/admin.py
rework/contrib/users/apps.py
rework/contrib/users/models.py
rework/contrib/users/tests.py
rework/contrib/users/urls.py
rework/contrib/users/views.py
rework/contrib/users/migrations/__init__.py
rework/core/__init__.py
rework/core/exceptions.py
rework/core/views.py
rework/core/__pycache__/__init__.cpython-311.pyc
rework/core/devops/__init__.py
rework/core/devops/fabric_tasks.py
rework/core/devops/hosts.py
rework/core/devops/tasks/__init__.py
rework/core/devops/tasks/deploy.py
rework/core/devops/tasks/environment.py
rework/core/devops/tasks/hi.py
rework/core/devops/tasks/setup_server.py
rework/core/management/__init__.py
rework/core/management/app.py
rework/core/management/deploy.py
rework/core/management/migrate.py
rework/core/management/project.py
rework/core/management/__pycache__/__init__.cpython-311.pyc
rework/core/management/__pycache__/app.cpython-311.pyc
rework/core/management/__pycache__/deploy.cpython-311.pyc
rework/core/management/__pycache__/migrate.cpython-311.pyc
rework/core/management/__pycache__/project.cpython-311.pyc
rework/core/management/handlers/__init__.py
rework/core/management/handlers/settings.py
rework/core/management/handlers/urls.py
rework/core/management/handlers/__pycache__/__init__.cpython-311.pyc
rework/core/management/handlers/__pycache__/settings.cpython-311.pyc
rework/core/management/handlers/__pycache__/urls.cpython-311.pyc
rework/core/quickmodel/__init__.py
rework/core/templates/.editorconfig.tpl
rework/core/templates/.env.dist.tpl
rework/core/templates/.env.tpl
rework/core/templates/.gitignore.tpl
rework/core/templates/.style.yapf.tpl
rework/core/templates/fabfile.py.tpl
rework/core/templates/requirements.txt.tpl
rework/core/templates/.deploy/nginx/project_prod.conf.tpl
rework/core/templates/.deploy/nginx/project_test.conf.tpl
django_rework-0.7.0.dist-info/LICENSE
django_rework-0.7.0.dist-info/METADATA
django_rework-0.7.0.dist-info/WHEEL
django_rework-0.7.0.dist-info/entry_points.txt
django_rework-0.7.0.dist-info/top_level.txt
django_rework-0.7.0.dist-info/RECORD
