Metadata-Version: 2.1
Name: django-rework
Version: 0.7.0
Summary: Non-verbose Django development experience
Home-page: https://github.com/rework-union/django-rework
Author: rework union
Author-email: josh.yu_8@live.com
License: MIT
Classifier: Development Status :: 5 - Production/Stable
Classifier: Environment :: Web Environment
Classifier: Framework :: Django
Classifier: Framework :: Django :: 3.2
Classifier: Framework :: Django :: 4.0
Classifier: Framework :: Django :: 4.1
Classifier: Framework :: Django :: 4.2
Classifier: Framework :: Django :: 5.0
Classifier: Intended Audience :: Developers
Classifier: License :: OSI Approved :: MIT License
Classifier: Operating System :: OS Independent
Classifier: Programming Language :: Python
Classifier: Programming Language :: Python :: 3
Classifier: Programming Language :: Python :: 3.8
Classifier: Programming Language :: Python :: 3.9
Classifier: Programming Language :: Python :: 3.10
Classifier: Programming Language :: Python :: 3.11
Classifier: Programming Language :: Python :: 3.12
Classifier: Programming Language :: Python :: 3 :: Only
Classifier: Topic :: Internet :: WWW/HTTP
License-File: LICENSE
Requires-Dist: Django<5.0,>=3.2
Requires-Dist: django-cors-headers<4.0,>=3.13.0
Requires-Dist: django-environ<1.0,>=0.9.0
Requires-Dist: django-filter<23,==22.1
Requires-Dist: django-mysql~=4.7
Requires-Dist: django-ninja<2.0,>=1.3.0
Requires-Dist: djangorestframework<4.0,>=3.15.2
Requires-Dist: djangorestframework-simplejwt~=5.3
Requires-Dist: drf-spectacular
Requires-Dist: fabric<3.0,>=2.7.1
Requires-Dist: Markdown~=3.4
Requires-Dist: mysqlclient~=2.1
Requires-Dist: patchwork~=1.0.1
Requires-Dist: Pillow~=9.0
Requires-Dist: drf-nested-routers~=0.93
Requires-Dist: wechatpy~=1.8
